openapi2awsapigateway/__init__.py
openapi2awsapigateway/main.py
openapi2awsapigateway/controllers/__init__.py
openapi2awsapigateway/controllers/adapt.py
openapi2awsapigateway/controllers/add.py
openapi2awsapigateway/controllers/base.py
openapi2awsapigateway/controllers/remove.py
openapi2awsapigateway/core/__init__.py
openapi2awsapigateway/core/exc.py
openapi2awsapigateway/core/version.py
openapi2awsapigateway/ext/__init__.py
openapi2awsapigateway/plugins/__init__.py
openapi2awsapigateway/templates/__init__.py
openapi2awsapigateway/templates/command1.jinja2
openapi2awsapigateway-0.0.5.dist-info/LICENSE.md
openapi2awsapigateway-0.0.5.dist-info/METADATA
openapi2awsapigateway-0.0.5.dist-info/WHEEL
openapi2awsapigateway-0.0.5.dist-info/entry_points.txt
openapi2awsapigateway-0.0.5.dist-info/top_level.txt
openapi2awsapigateway-0.0.5.dist-info/RECORD
