Metadata-Version: 2.1
Name: openapi2awsapigateway
Version: 0.0.5
Summary: Adapt OpenAPI and Swagger files to include AWS API Gateway Integrations
Home-page: https://github.com/athomegroup/openapi2awsapigateway
Author: Joao Lopes
Author-email: joao.lopes@athome.eu
License: unlicensed
Platform: UNKNOWN
License-File: LICENSE.md
Requires-Dist: cement (==3.0.6)
Requires-Dist: jinja2
Requires-Dist: pyyaml (==6.0)
Requires-Dist: colorlog
